flask_variable_manager/__init__.py
flask_variable_manager/extension/__init__.py
flask_variable_manager/extension/variable_manager.py
flask_variable_manager/tests/__init__.py
flask_variable_manager/tests/test_vm.py
flask_variable_manager-0.4.1.dist-info/LICENSE
flask_variable_manager-0.4.1.dist-info/METADATA
flask_variable_manager-0.4.1.dist-info/WHEEL
flask_variable_manager-0.4.1.dist-info/top_level.txt
flask_variable_manager-0.4.1.dist-info/RECORD
