Metadata-Version: 2.1
Name: flask-variable-manager
Version: 0.4.1
Summary: Create a variable manager in flask, enter values in python, and use values on the jinja template.
Author-email: minwook-shin <minwook0106@gmail.com>
Project-URL: Homepage, https://github.com/minwook-shin/flask-variable-manager
Project-URL: Bug Tracker, https://github.com/minwook-shin/flask-variable-manager/issues
Classifier: Programming Language :: Python :: 3
Classifier: License :: OSI Approved :: MIT License
Classifier: Operating System :: OS Independent
Classifier: Framework :: Flask
Requires-Python: >=3.9
License-File: LICENSE
Requires-Dist: flask ==3.0.3
Requires-Dist: Jinja2 ==3.1.3
Provides-Extra: dev
Requires-Dist: flasgger ==0.9.7b2 ; extra == 'dev'
Requires-Dist: build ==1.2.1 ; extra == 'dev'
Requires-Dist: twine ==5.0.0 ; extra == 'dev'
